[
  {
    "_id": "69d16583b964434b3c703376",
    "name": "The Assembled",
    "slug": "the-assembled"
  },
  {
    "_id": "69d16583b964434b3c703377",
    "name": "The Athletes",
    "slug": "the-athletes"
  },
  {
    "_id": "69d16583b964434b3c703378",
    "name": "The Cut",
    "slug": "the-cut"
  },
  {
    "_id": "69d16583b964434b3c703379",
    "name": "The Cut Edge",
    "slug": "the-cut-edge"
  },
  {
    "_id": "69d16583b964434b3c70337a",
    "name": "The Edge",
    "slug": "the-edge"
  },
  {
    "_id": "69d16583b964434b3c70337b",
    "name": "The Flow",
    "slug": "the-flow"
  },
  {
    "_id": "69d16583b964434b3c70337c",
    "name": "The Layered",
    "slug": "the-layered"
  },
  {
    "_id": "69d16583b964434b3c70337d",
    "name": "The Obsidian",
    "slug": "the-obsidian"
  },
  {
    "_id": "69d16583b964434b3c70337e",
    "name": "The Office",
    "slug": "the-office"
  },
  {
    "_id": "69d16583b964434b3c70337f",
    "name": "The Paper Knife",
    "slug": "the-paper-knife"
  },
  {
    "_id": "69d16583b964434b3c703380",
    "name": "The Ruler",
    "slug": "the-ruler"
  },
  {
    "_id": "69d16583b964434b3c703381",
    "name": "The Set Square",
    "slug": "the-set-square"
  },
  {
    "_id": "69d16583b964434b3c703382",
    "name": "The Snorkel",
    "slug": "the-snorkel"
  },
  {
    "_id": "69d16583b964434b3c703383",
    "name": "The Soap",
    "slug": "the-soap"
  },
  {
    "_id": "69d16583b964434b3c703384",
    "name": "The Vertebra",
    "slug": "the-vertebra"
  }
]